LICENSE
MANIFEST.in
README.rst
setup.py
wanish/__init__.py
wanish/cleaner.py
wanish/encoding.py
wanish/images.py
wanish/langid.py
wanish/summarizer.py
wanish/title.py
wanish.egg-info/PKG-INFO
wanish.egg-info/SOURCES.txt
wanish.egg-info/dependency_links.txt
wanish.egg-info/requires.txt
wanish.egg-info/top_level.txt