Metadata-Version: 1.1
Name: wanish
Version: 0.6.2
Summary: open source implementation of summly
Home-page: https://github.com/reefeed/wanish
Author: Igor Gorschal
Author-email: gorschal@gmail.com
License: MIT
Keywords: summly,bookie,content,HTML,parsing,readability,readable
Platform: UNKNOWN
Classifier: Development Status :: 5 - Production/Stable
Classifier: Intended Audience :: Developers
Classifier: License :: OSI Approved :: MIT License
Classifier: Operating System :: OS Independent
Classifier: Programming Language :: Python
Classifier: Programming Language :: Python :: 3.3
Classifier: Programming Language :: Python :: 3.4
Classifier: Programming Language :: Python :: 3.5
Classifier: Topic :: Internet :: WWW/HTTP
Classifier: Topic :: Software Development :: Pre-processors
Classifier: Topic :: Text Processing :: Filters
Classifier: Topic :: Text Processing :: Markup :: HTML
